LICENSE
README.md
commonstrings.pyx
pyproject.toml
setup.py
./common_multiple_strings/auxiliary/alphabet.cpp
./common_multiple_strings/auxiliary/suffix_tree_simple.cpp
./common_multiple_strings/auxiliary/utf8.cpp
common_multiple_strings/common_multiple_strings.h
common_multiple_strings/auxiliary/alphabet.h
common_multiple_strings/auxiliary/suffix_tree_simple.h
common_multiple_strings/auxiliary/utf8.h
common_multiple_strings/auxiliary/utf8/checked.h
common_multiple_strings/auxiliary/utf8/core.h
common_multiple_strings/auxiliary/utf8/unchecked.h
commonstrings.egg-info/PKG-INFO
commonstrings.egg-info/SOURCES.txt
commonstrings.egg-info/dependency_links.txt
commonstrings.egg-info/requires.txt
commonstrings.egg-info/top_level.txt