Metadata-Version: 2.1
Name: commonstrings
Version: 1.4
Summary: Common Strings of Multiple Strings - A fast Python library written in C++
Home-page: https://github.com/phamthivan2996/commonstrings
Author: Pham Van
Author-email: Pham Van <kagum2996@gmail.com>
Project-URL: Source, https://github.com/phamthivan2996/commonstrings
Project-URL: Homepage, https://github.com/phamthivan2996/commonstrings
Project-URL: Issues, https://github.com/phamthivan2996/commonstrings/issues
Project-URL: Repository, https://github.com/phamthivan2996/commonstrings.git
Classifier: Programming Language :: Python :: 3
Classifier: License :: OSI Approved :: MIT License
Classifier: Operating System :: OS Independent
Requires-Python: >=3.8
License-File: LICENSE
Requires-Dist: numpy
Requires-Dist: scipy
